Catactor/__init__.py
Catactor/mini_catactor.py
Catactor/pseudo_bulk.py
Catactor-0.1.2.dist-info/LICENSE
Catactor-0.1.2.dist-info/METADATA
Catactor-0.1.2.dist-info/WHEEL
Catactor-0.1.2.dist-info/top_level.txt
Catactor-0.1.2.dist-info/RECORD
