Metadata-Version: 2.1
Name: Catactor
Version: 0.1.2
Summary: scATAC-seq analysis using meta-analytic marker genes
Home-page: https://github.com/carushi/Catactor/
Author: carushi
Author-email: rkawaguc@cshl.edu
License: MIT
Platform: UNKNOWN
